peerplays/__init__.py
peerplays/account.py
peerplays/amount.py
peerplays/asset.py
peerplays/bet.py
peerplays/bettingmarket.py
peerplays/bettingmarketgroup.py
peerplays/block.py
peerplays/blockchain.py
peerplays/blockchainobject.py
peerplays/committee.py
peerplays/event.py
peerplays/eventgroup.py
peerplays/exceptions.py
peerplays/genesisbalance.py
peerplays/instance.py
peerplays/market.py
peerplays/memo.py
peerplays/message.py
peerplays/notify.py
peerplays/peerplays.py
peerplays/peerplays2.py
peerplays/price.py
peerplays/proposal.py
peerplays/rule.py
peerplays/son.py
peerplays/sport.py
peerplays/storage.py
peerplays/transactionbuilder.py
peerplays/utils.py
peerplays/wallet.py
peerplays/witness.py
peerplays/cli/__init__.py
peerplays/cli/account.py
peerplays/cli/asset.py
peerplays/cli/bookie.py
peerplays/cli/bos.py
peerplays/cli/cli.py
peerplays/cli/committee.py
peerplays/cli/decorators.py
peerplays/cli/info.py
peerplays/cli/main.py
peerplays/cli/message.py
peerplays/cli/proposal.py
peerplays/cli/rpc.py
peerplays/cli/ui.py
peerplays/cli/wallet.py
peerplays/cli/witness.py
peerplaysapi/__init__.py
peerplaysapi/exceptions.py
peerplaysapi/node.py
peerplaysapi/wallet.py
peerplaysapi/websocket.py
peerplaysbase/__init__.py
peerplaysbase/account.py
peerplaysbase/asset_permissions.py
peerplaysbase/chains.py
peerplaysbase/memo.py
peerplaysbase/objects.py
peerplaysbase/objecttypes.py
peerplaysbase/operationids.py
peerplaysbase/operations.py
peerplaysbase/signedtransactions.py
peerplaysbase/types.py
peerplays-0.5.3.dist-info/LICENSE.txt
peerplays-0.5.3.dist-info/METADATA
peerplays-0.5.3.dist-info/WHEEL
peerplays-0.5.3.dist-info/entry_points.txt
peerplays-0.5.3.dist-info/top_level.txt
peerplays-0.5.3.dist-info/RECORD
