Metadata-Version: 2.1
Name: peerplays
Version: 0.5.3
Summary: Python library for PEERPLAYS
Home-page: https://gitlab.com/PBSA/tools-libs/python-peerplays
Author: PBSA and contributors. Original by Fabian Schuh.
Author-email: info@pbsa.info
Maintainer: PBSA
Maintainer-email: info@pbsa.info
Keywords: peerplays,library,api,rpc
Classifier: License :: OSI Approved :: MIT License
Classifier: Operating System :: OS Independent
Classifier: Programming Language :: Python :: 3
Classifier: Development Status :: 3 - Alpha
Classifier: Intended Audience :: Developers
Classifier: Intended Audience :: System Administrators
Classifier: Topic :: Games/Entertainment
License-File: LICENSE.txt
Requires-Dist: scrypt (==0.8.13)
Requires-Dist: appdirs (==1.4.3)
Requires-Dist: graphenelib (==1.5.4)
Requires-Dist: prettytable
Requires-Dist: events
Requires-Dist: pyyaml
Requires-Dist: click
Requires-Dist: treelib
Requires-Dist: ecdsa (==0.18)
Requires-Dist: websockets (>=10.0)
